tsectc/__init__.py
tsectc/tsectc.py
tsectc-0.0.2.dist-info/LICENCE.txt
tsectc-0.0.2.dist-info/METADATA
tsectc-0.0.2.dist-info/WHEEL
tsectc-0.0.2.dist-info/top_level.txt
tsectc-0.0.2.dist-info/RECORD
